setup.py
Trie_impl/__init__.py
Trie_impl.egg-info/PKG-INFO
Trie_impl.egg-info/SOURCES.txt
Trie_impl.egg-info/dependency_links.txt
Trie_impl.egg-info/not-zip-safe
Trie_impl.egg-info/top_level.txt