Metadata-Version: 1.0
Name: Trie-impl
Version: 0.1
Summary: My Trie implementation
Home-page: UNKNOWN
Author: KC
Author-email: vmanikes@hawk.it.edu
License: UNKNOWN
Platform: UNKNOWN
